override_autonow/__init__.py
override_autonow/context_decorator.py
django_override_autonow-0.0.1.dist-info/LICENSE
django_override_autonow-0.0.1.dist-info/METADATA
django_override_autonow-0.0.1.dist-info/WHEEL
django_override_autonow-0.0.1.dist-info/top_level.txt
django_override_autonow-0.0.1.dist-info/RECORD
