Metadata-Version: 2.1
Name: django-override-autonow
Version: 0.0.1
Summary: Temporarily disable auto_now and auto_now_add option in Django's DateField and DateTimeField, so that you can save the desired value to these fields.
Home-page: https://github.com/yukihira1992/django-override-autonow
Author: Takayuki Hirayama
Author-email: th.windbell+github@gmail.com
License: MIT License
Project-URL: Bug Tracker, https://github.com/yukihira1992/django-override-autonow/issues
Keywords: django,pytest,unittest,auto_now,auto_now_add,override,date,datetime
Platform: UNKNOWN
Classifier: Development Status :: 1 - Planning
Classifier: Framework :: Django
Classifier: Framework :: Django :: 2.2
Classifier: Framework :: Django :: 3.0
Classifier: Framework :: Django :: 3.1
Classifier: Framework :: Django :: 3.2
Classifier: Framework :: Django :: 4.0
Classifier: Framework :: Pytest
Classifier: Intended Audience :: Developers
Classifier: License :: OSI Approved :: MIT License
Classifier: Operating System :: OS Independent
Classifier: Programming Language :: Python
Classifier: Programming Language :: Python :: 3
Classifier: Programming Language :: Python :: 3 :: Only
Classifier: Programming Language :: Python :: 3.7
Classifier: Programming Language :: Python :: 3.8
Classifier: Programming Language :: Python :: 3.9
Classifier: Programming Language :: Python :: 3.10
Classifier: Topic :: Software Development
Classifier: Topic :: Software Development :: Testing
Classifier: Topic :: Software Development :: Testing :: Mocking
Classifier: Topic :: Software Development :: Testing :: Unit
Requires-Python: >=3.7
License-File: LICENSE
Requires-Dist: Django (>=2.2)
Provides-Extra: testing
Requires-Dist: pytest ; extra == 'testing'
Requires-Dist: pytest-django ; extra == 'testing'
